Spruce_http_common-0.1.3-py2.7-nspkg.pth
spruce/http/_methods.py
spruce/http/__init__.py
spruce/http/status/_core.py
spruce/http/status/__init__.py
Spruce_http_common-0.1.3.dist-info/top_level.txt
Spruce_http_common-0.1.3.dist-info/RECORD
Spruce_http_common-0.1.3.dist-info/pydist.json
Spruce_http_common-0.1.3.dist-info/WHEEL
Spruce_http_common-0.1.3.dist-info/namespace_packages.txt
Spruce_http_common-0.1.3.dist-info/METADATA
Spruce_http_common-0.1.3.dist-info/entry_points.txt
Spruce_http_common-0.1.3.dist-info/DESCRIPTION.rst
