Metadata-Version: 2.0
Name: Spruce-http-common
Version: 0.1.3
Summary: Hypertext transfer protocol (HTTP), common components
Home-page: UNKNOWN
Author: Ivan D Vasin
Author-email: nisavid@gmail.com
License: GNU LESSER GENERAL PUBLIC LICENSE
